denorm/__init__.py
denorm/agg.py
denorm/agg_change.py
denorm/agg_clean.py
denorm/agg_common.py
denorm/agg_defer.py
denorm/agg_query.py
denorm/format.py
denorm/graph.py
denorm/join.py
denorm/join_async.py
denorm/join_change.py
denorm/join_common.py
denorm/join_defer.py
denorm/join_key.py
denorm/join_lock.py
denorm/join_plain_target.py
denorm/join_query.py
denorm/join_refresh_function.py
denorm/join_table_target.py
denorm/join_target_table.py
denorm/key.py
denorm/sql.py
denorm/sql_query.py
denorm/string.py
denorm/version.py
denorm/cli/__init__.py
denorm/cli/common.py
denorm/cli/create_agg.py
denorm/cli/create_join.py
denorm/cli/create_key.py
denorm/cli/main.py
denorm/formats/__init__.py
denorm/formats/agg.json
denorm/formats/agg.py
denorm/formats/join.json
denorm/formats/join.py
denorm/formats/key.py
denorm/json/__init__.py
denorm/resource/__init__.py
denorm-2.4.3.dist-info/LICENSE.txt
denorm-2.4.3.dist-info/METADATA
denorm-2.4.3.dist-info/WHEEL
denorm-2.4.3.dist-info/entry_points.txt
denorm-2.4.3.dist-info/top_level.txt
denorm-2.4.3.dist-info/RECORD
