Metadata-Version: 2.1
Name: denorm
Version: 2.4.3
Summary: Maintain denormalized and aggregated PostgreSQL tables
Home-page: https://github.com/rivethealth/denorm
Author: Rivet Health
Author-email: ops@rivethealth.com
License: UNKNOWN
Project-URL: Issues, https://github.com/rivethealth/denorm/issues
Platform: UNKNOWN
Classifier: License :: OSI Approved :: MIT License
Classifier: Operating System :: OS Independent
Classifier: Programming Language :: Python
Classifier: Programming Language :: Python :: 3
Classifier: Programming Language :: Python :: 2
Requires-Dist: dataclasses-json
Requires-Dist: jsonschema
Requires-Dist: pg-sql (>=0.0.1)
Provides-Extra: dev
Requires-Dist: black ; extra == 'dev'
Requires-Dist: isort ; extra == 'dev'
Requires-Dist: jsonschema2md ; extra == 'dev'
Requires-Dist: pytest ; extra == 'dev'
Requires-Dist: pytest-env ; extra == 'dev'
